django-template-tag/__init__.py
django-template-tag/linked_list.py
tests/__init__.py
django_template_tag-1.0.0.dist-info/LICENSE
django_template_tag-1.0.0.dist-info/METADATA
django_template_tag-1.0.0.dist-info/WHEEL
django_template_tag-1.0.0.dist-info/top_level.txt
django_template_tag-1.0.0.dist-info/RECORD
