Metadata-Version: 2.1
Name: django-template-tag
Version: 1.0.0
Summary: package for Django custom template tags
Home-page: https://github.com/bairavand/django-template-tag
Author: Bairavan
Author-email: bairavand@gmail.com
Project-URL: Bug Tracker, https://github.com/bairavand/django-template-tag/issues
Classifier: Programming Language :: Python :: 3
Classifier: License :: OSI Approved :: MIT License
Classifier: Operating System :: OS Independent
Requires-Python: >=3.6
License-File: LICENSE
